nebulagraph_mcp_server/__init__.py
nebulagraph_mcp_server/server.py
nebulagraph_mcp_server-0.1.1.dist-info/METADATA
nebulagraph_mcp_server-0.1.1.dist-info/WHEEL
nebulagraph_mcp_server-0.1.1.dist-info/entry_points.txt
nebulagraph_mcp_server-0.1.1.dist-info/licenses/LICENSE
nebulagraph_mcp_server-0.1.1.dist-info/RECORD
